djangocms_multimenus-0.2.1.dist-info/DESCRIPTION.rst
djangocms_multimenus-0.2.1.dist-info/METADATA
djangocms_multimenus-0.2.1.dist-info/RECORD
djangocms_multimenus-0.2.1.dist-info/WHEEL
djangocms_multimenus-0.2.1.dist-info/metadata.json
djangocms_multimenus-0.2.1.dist-info/top_level.txt
multimenus/__init__.py
multimenus/admin.py
multimenus/apps.py
multimenus/cms_toolbars.py
multimenus/enums.py
multimenus/forms.py
multimenus/models.py
multimenus/locale/pl/LC_MESSAGES/django.mo
multimenus/locale/pl/LC_MESSAGES/django.po
multimenus/migrations/0001_initial.py
multimenus/migrations/0002_auto_20170420_2006.py
multimenus/migrations/0003_menuitem_site.py
multimenus/migrations/0004_auto_20170530_1323.py
multimenus/migrations/__init__.py
multimenus/templates/.DS_Store
multimenus/templates/multimenus/.DS_Store
multimenus/templates/multimenus/menu.html
multimenus/templatetags/__init__.py
multimenus/templatetags/multimenus.py
