Metadata-Version: 2.0
Name: djangocms-multimenus
Version: 0.2.1
Summary: Multiple named menus support for DjangoCMS
Home-page: https://github.com/elcodo/djangocms-multimenus
Author: ELCODO
Author-email: info@elcodo.pl
License: LICENSE.txt
Platform: OS Independent
Classifier: Development Status :: 2 - Pre-Alpha
Classifier: Environment :: Web Environment
Classifier: Framework :: Django
Classifier: Intended Audience :: Developers
Classifier: License :: OSI Approved :: BSD License
Classifier: Operating System :: OS Independent
Classifier: Programming Language :: Python :: 3
Classifier: Topic :: Internet :: WWW/HTTP :: Dynamic Content
Classifier: Topic :: Software Development
Classifier: Topic :: Software Development :: Libraries :: Application Frameworks
Requires-Dist: aldryn-translation-tools
Requires-Dist: django-cms
Requires-Dist: django-parler
Requires-Dist: django-treebeard
